dconfusion/DConfusion.py
dconfusion/__init__.py
dconfusion/consistency.py
dconfusion/core.py
dconfusion/io.py
dconfusion/metrics.py
dconfusion/statistics.py
dconfusion/validation.py
dconfusion/visualization.py
dconfusion/warnings.py
dconfusion-1.1.dist-info/licenses/LICENSE
dconfusion-1.1.dist-info/METADATA
dconfusion-1.1.dist-info/WHEEL
dconfusion-1.1.dist-info/top_level.txt
dconfusion-1.1.dist-info/RECORD
