Metadata-Version: 2.4
Name: dconfusion
Version: 1.1
Summary: Comprehensive confusion matrix analysis with metric inference, statistical testing, and cost-sensitive evaluation
Author-email: Surya Gundavarapu <surya_gundavarapu@yahoo.com>, Matthew Lanham <mlanham1@butler.edu>, Aadya Pawar <pawar17@purdue.edu>
Maintainer-email: Matthew Lanham <mlanham1@butler.edu>, Aadya Pawar <pawar17@purdue.edu>
License: MIT License
Project-URL: Homepage, https://github.com/sgundava/dconfusion
Project-URL: Repository, https://github.com/sgundava/dconfusion
Keywords: confusion-matrix,classification,machine-learning,metrics,statistics,model-evaluation,performance-analysis,metric-inference,cost-sensitive,bootstrap,mcnemar,consistency-testing
Classifier: Development Status :: 5 - Production/Stable
Classifier: Intended Audience :: Developers
Classifier: Intended Audience :: Education
Classifier: Intended Audience :: Science/Research
Classifier: Intended Audience :: Healthcare Industry
Classifier: Natural Language :: English
Classifier: Operating System :: OS Independent
Classifier: Programming Language :: Python :: 3
Classifier: Programming Language :: Python :: 3.8
Classifier: Programming Language :: Python :: 3.9
Classifier: Programming Language :: Python :: 3.10
Classifier: Programming Language :: Python :: 3.11
Classifier: Programming Language :: Python :: 3.12
Classifier: Topic :: Scientific/Engineering
Classifier: Topic :: Scientific/Engineering :: Artificial Intelligence
Classifier: Topic :: Software Development :: Libraries :: Python Modules
Classifier: Typing :: Typed
Requires-Python: >=3.8
License-File: LICENSE
Requires-Dist: numpy
Requires-Dist: matplotlib
Requires-Dist: scipy
Provides-Extra: consistency
Requires-Dist: mlscorecheck>=1.0.0; extra == "consistency"
Provides-Extra: all
Requires-Dist: mlscorecheck>=1.0.0; extra == "all"
Dynamic: license-file
